{
  "$schema": "https://developer.microsoft.com/json-schemas/fabric/item/report/definition/visualContainer/2.1.0/schema.json",
  "name": "c2ea1b299eec2d8c0b7e",
  "position": {
    "x": 0,
    "y": 0,
    "z": 22000,
    "height": 216.18219461697723,
    "width": 530.55072463768113,
    "tabOrder": 1000
  },
  "visual": {
    "visualType": "pivotTable",
    "query": {
      "queryState": {
        "Rows": {
          "projections": [
            {
              "field": {
                "Column": {
                  "Expression": {
                    "SourceRef": {
                      "Entity": "Sales Channel"
                    }
                  },
                  "Property": "Sales Channel"
                }
              },
              "queryRef": "Sales Channel.Sales Channel",
              "nativeQueryRef": "Sales Channel",
              "active": true
            }
          ]
        },
        "Values": {
          "projections": [
            {
              "field": {
                "Measure": {
                  "Expression": {
                    "SourceRef": {
                      "Entity": "1 - Revenue"
                    }
                  },
                  "Property": "RP CY CPP"
                }
              },
              "queryRef": "1 - Revenue.RP CY CPP",
              "nativeQueryRef": "Actual cpp",
              "displayName": "Actual cpp"
            },
            {
              "field": {
                "Measure": {
                  "Expression": {
                    "SourceRef": {
                      "Entity": "1 - Revenue"
                    }
                  },
                  "Property": "∆ Price"
                }
              },
              "queryRef": "1 - Revenue.∆ Price",
              "nativeQueryRef": "∆ Price $(m)",
              "displayName": "∆ Price $(m)"
            },
            {
              "field": {
                "Measure": {
                  "Expression": {
                    "SourceRef": {
                      "Entity": "1 - Revenue"
                    }
                  },
                  "Property": "∆ Vol."
                }
              },
              "queryRef": "1 - Revenue.∆ Vol.",
              "nativeQueryRef": "∆ Vol. lbs(m)",
              "displayName": "∆ Vol. lbs(m)"
            },
            {
              "field": {
                "Measure": {
                  "Expression": {
                    "SourceRef": {
                      "Entity": "1 - Revenue"
                    }
                  },
                  "Property": "Price Variance"
                }
              },
              "queryRef": "1 - Revenue.Price Variance",
              "nativeQueryRef": "Price Var. $(m)",
              "displayName": "Price Var. $(m)"
            },
            {
              "field": {
                "Measure": {
                  "Expression": {
                    "SourceRef": {
                      "Entity": "1 - Revenue"
                    }
                  },
                  "Property": "Volume Variance"
                }
              },
              "queryRef": "1 - Revenue.Volume Variance",
              "nativeQueryRef": "Vol. Var. $(m)",
              "displayName": "Vol. Var. $(m)"
            },
            {
              "field": {
                "Measure": {
                  "Expression": {
                    "SourceRef": {
                      "Entity": "1 - Revenue"
                    }
                  },
                  "Property": "Total Variance"
                }
              },
              "queryRef": "1 - Revenue.Total Variance",
              "nativeQueryRef": "Total Var. $(m)",
              "displayName": "Total Var. $(m)"
            }
          ]
        }
      }
    },
    "objects": {
      "columnWidth": [
        {
          "properties": {
            "value": {
              "expr": {
                "Literal": {
                  "Value": "81.01370058666755D"
                }
              }
            }
          },
          "selector": {
            "metadata": "1 - Revenue.RP PY SV Actual"
          }
        },
        {
          "properties": {
            "value": {
              "expr": {
                "Literal": {
                  "Value": "69.39036360086214D"
                }
              }
            }
          },
          "selector": {
            "metadata": "Sales Channel.Sales Channel"
          }
        },
        {
          "properties": {
            "value": {
              "expr": {
                "Literal": {
                  "Value": "67.6879755087972D"
                }
              }
            }
          },
          "selector": {
            "metadata": "1 - Revenue.RP CY CPP"
          }
        },
        {
          "properties": {
            "value": {
              "expr": {
                "Literal": {
                  "Value": "68.45322576339807D"
                }
              }
            }
          },
          "selector": {
            "metadata": "1 - Revenue.Price Variance"
          }
        },
        {
          "properties": {
            "value": {
              "expr": {
                "Literal": {
                  "Value": "69.82434481598983D"
                }
              }
            }
          },
          "selector": {
            "metadata": "1 - Revenue.Volume Variance"
          }
        },
        {
          "properties": {
            "value": {
              "expr": {
                "Literal": {
                  "Value": "78.96859488576855D"
                }
              }
            }
          },
          "selector": {
            "metadata": "1 - Revenue.Total Variance"
          }
        },
        {
          "properties": {
            "value": {
              "expr": {
                "Literal": {
                  "Value": "73.20224972039853D"
                }
              }
            }
          },
          "selector": {
            "metadata": "1 - Revenue.∆ Price"
          }
        },
        {
          "properties": {
            "value": {
              "expr": {
                "Literal": {
                  "Value": "81.93908793700287D"
                }
              }
            }
          },
          "selector": {
            "metadata": "1 - Revenue.∆ Vol."
          }
        }
      ],
      "columnHeaders": [
        {
          "properties": {
            "autoSizeColumnWidth": {
              "expr": {
                "Literal": {
                  "Value": "true"
                }
              }
            },
            "fontSize": {
              "expr": {
                "Literal": {
                  "Value": "9D"
                }
              }
            },
            "bold": {
              "expr": {
                "Literal": {
                  "Value": "true"
                }
              }
            },
            "alignment": {
              "expr": {
                "Literal": {
                  "Value": "'Center'"
                }
              }
            },
            "wordWrap": {
              "expr": {
                "Literal": {
                  "Value": "true"
                }
              }
            }
          }
        }
      ],
      "values": [
        {
          "properties": {
            "fontSize": {
              "expr": {
                "Literal": {
                  "Value": "11D"
                }
              }
            },
            "valuesOnRow": {
              "expr": {
                "Literal": {
                  "Value": "false"
                }
              }
            }
          }
        },
        {
          "properties": {
            "backColor": {
              "solid": {
                "color": {
                  "expr": {
                    "Conditional": {
                      "Cases": [
                        {
                          "Condition": {
                            "And": {
                              "Left": {
                                "Comparison": {
                                  "ComparisonKind": 2,
                                  "Left": {
                                    "Measure": {
                                      "Expression": {
                                        "SourceRef": {
                                          "Entity": "1 - Revenue"
                                        }
                                      },
                                      "Property": "Price Variance"
                                    }
                                  },
                                  "Right": {
                                    "Literal": {
                                      "Value": "-10000000000000000D"
                                    }
                                  }
                                }
                              },
                              "Right": {
                                "Comparison": {
                                  "ComparisonKind": 3,
                                  "Left": {
                                    "Measure": {
                                      "Expression": {
                                        "SourceRef": {
                                          "Entity": "1 - Revenue"
                                        }
                                      },
                                      "Property": "Price Variance"
                                    }
                                  },
                                  "Right": {
                                    "Literal": {
                                      "Value": "0D"
                                    }
                                  }
                                }
                              }
                            }
                          },
                          "Value": {
                            "Literal": {
                              "Value": "'#DE5858'"
                            }
                          }
                        }
                      ]
                    }
                  }
                }
              }
            }
          },
          "selector": {
            "data": [
              {
                "dataViewWildcard": {
                  "matchingOption": 0
                }
              }
            ],
            "metadata": "1 - Revenue.Price Variance"
          }
        },
        {
          "properties": {
            "backColor": {
              "solid": {
                "color": {
                  "expr": {
                    "Conditional": {
                      "Cases": [
                        {
                          "Condition": {
                            "Comparison": {
                              "ComparisonKind": 3,
                              "Left": {
                                "Measure": {
                                  "Expression": {
                                    "SourceRef": {
                                      "Entity": "1 - Revenue"
                                    }
                                  },
                                  "Property": "Volume Variance"
                                }
                              },
                              "Right": {
                                "Literal": {
                                  "Value": "0D"
                                }
                              }
                            }
                          },
                          "Value": {
                            "Literal": {
                              "Value": "'#DE5858'"
                            }
                          }
                        }
                      ]
                    }
                  }
                }
              }
            }
          },
          "selector": {
            "data": [
              {
                "dataViewWildcard": {
                  "matchingOption": 0
                }
              }
            ],
            "metadata": "1 - Revenue.Volume Variance"
          }
        },
        {
          "properties": {
            "backColor": {
              "solid": {
                "color": {
                  "expr": {
                    "Conditional": {
                      "Cases": [
                        {
                          "Condition": {
                            "And": {
                              "Left": {
                                "Comparison": {
                                  "ComparisonKind": 2,
                                  "Left": {
                                    "Measure": {
                                      "Expression": {
                                        "SourceRef": {
                                          "Entity": "1 - Revenue"
                                        }
                                      },
                                      "Property": "Total Variance"
                                    }
                                  },
                                  "Right": {
                                    "Literal": {
                                      "Value": "-9999999999999D"
                                    }
                                  }
                                }
                              },
                              "Right": {
                                "Comparison": {
                                  "ComparisonKind": 3,
                                  "Left": {
                                    "Measure": {
                                      "Expression": {
                                        "SourceRef": {
                                          "Entity": "1 - Revenue"
                                        }
                                      },
                                      "Property": "Total Variance"
                                    }
                                  },
                                  "Right": {
                                    "Literal": {
                                      "Value": "0D"
                                    }
                                  }
                                }
                              }
                            }
                          },
                          "Value": {
                            "Literal": {
                              "Value": "'#DE5858'"
                            }
                          }
                        }
                      ]
                    }
                  }
                }
              }
            }
          },
          "selector": {
            "data": [
              {
                "dataViewWildcard": {
                  "matchingOption": 0
                }
              }
            ],
            "metadata": "1 - Revenue.Total Variance"
          }
        },
        {
          "properties": {
            "icon": {
              "kind": "Icon",
              "layout": {
                "expr": {
                  "Literal": {
                    "Value": "'Before'"
                  }
                }
              },
              "verticalAlignment": {
                "expr": {
                  "Literal": {
                    "Value": "'Top'"
                  }
                }
              },
              "value": {
                "expr": {
                  "Conditional": {
                    "Cases": [
                      {
                        "Condition": {
                          "And": {
                            "Left": {
                              "Comparison": {
                                "ComparisonKind": 2,
                                "Left": {
                                  "Measure": {
                                    "Expression": {
                                      "SourceRef": {
                                        "Entity": "1 - Revenue"
                                      }
                                    },
                                    "Property": "∆ Price"
                                  }
                                },
                                "Right": {
                                  "Literal": {
                                    "Value": "-99999999999999D"
                                  }
                                }
                              }
                            },
                            "Right": {
                              "Comparison": {
                                "ComparisonKind": 3,
                                "Left": {
                                  "Measure": {
                                    "Expression": {
                                      "SourceRef": {
                                        "Entity": "1 - Revenue"
                                      }
                                    },
                                    "Property": "∆ Price"
                                  }
                                },
                                "Right": {
                                  "Literal": {
                                    "Value": "0D"
                                  }
                                }
                              }
                            }
                          }
                        },
                        "Value": {
                          "Literal": {
                            "Value": "'TriangleLow'"
                          }
                        }
                      }
                    ]
                  }
                }
              }
            }
          },
          "selector": {
            "data": [
              {
                "dataViewWildcard": {
                  "matchingOption": 1
                }
              }
            ],
            "metadata": "1 - Revenue.∆ Price"
          }
        },
        {
          "properties": {
            "icon": {
              "kind": "Icon",
              "layout": {
                "expr": {
                  "Literal": {
                    "Value": "'Before'"
                  }
                }
              },
              "verticalAlignment": {
                "expr": {
                  "Literal": {
                    "Value": "'Top'"
                  }
                }
              },
              "value": {
                "expr": {
                  "Conditional": {
                    "Cases": [
                      {
                        "Condition": {
                          "And": {
                            "Left": {
                              "Comparison": {
                                "ComparisonKind": 2,
                                "Left": {
                                  "Measure": {
                                    "Expression": {
                                      "SourceRef": {
                                        "Entity": "1 - Revenue"
                                      }
                                    },
                                    "Property": "∆ Vol."
                                  }
                                },
                                "Right": {
                                  "Literal": {
                                    "Value": "-99999999999D"
                                  }
                                }
                              }
                            },
                            "Right": {
                              "Comparison": {
                                "ComparisonKind": 3,
                                "Left": {
                                  "Measure": {
                                    "Expression": {
                                      "SourceRef": {
                                        "Entity": "1 - Revenue"
                                      }
                                    },
                                    "Property": "∆ Vol."
                                  }
                                },
                                "Right": {
                                  "Literal": {
                                    "Value": "0D"
                                  }
                                }
                              }
                            }
                          }
                        },
                        "Value": {
                          "Literal": {
                            "Value": "'TriangleLow'"
                          }
                        }
                      }
                    ]
                  }
                }
              }
            }
          },
          "selector": {
            "data": [
              {
                "dataViewWildcard": {
                  "matchingOption": 0
                }
              }
            ],
            "metadata": "1 - Revenue.∆ Vol."
          }
        },
        {
          "properties": {},
          "selector": {
            "data": [
              {
                "dataViewWildcard": {
                  "matchingOption": 1
                }
              }
            ],
            "metadata": "1 - Revenue.Price Variance"
          }
        }
      ],
      "columnFormatting": [
        {
          "properties": {
            "alignment": {
              "expr": {
                "Literal": {
                  "Value": "'Center'"
                }
              }
            },
            "styleHeader": {
              "expr": {
                "Literal": {
                  "Value": "true"
                }
              }
            },
            "styleValues": {
              "expr": {
                "Literal": {
                  "Value": "false"
                }
              }
            },
            "styleSubtotals": {
              "expr": {
                "Literal": {
                  "Value": "false"
                }
              }
            },
            "styleTotal": {
              "expr": {
                "Literal": {
                  "Value": "false"
                }
              }
            }
          },
          "selector": {
            "metadata": "1 - Revenue.RP CY CPP"
          }
        },
        {
          "properties": {
            "alignment": {
              "expr": {
                "Literal": {
                  "Value": "'Center'"
                }
              }
            },
            "styleHeader": {
              "expr": {
                "Literal": {
                  "Value": "true"
                }
              }
            },
            "styleValues": {
              "expr": {
                "Literal": {
                  "Value": "false"
                }
              }
            },
            "styleSubtotals": {
              "expr": {
                "Literal": {
                  "Value": "false"
                }
              }
            },
            "styleTotal": {
              "expr": {
                "Literal": {
                  "Value": "false"
                }
              }
            }
          },
          "selector": {
            "metadata": "1 - Revenue.Price Variance"
          }
        },
        {
          "properties": {
            "alignment": {
              "expr": {
                "Literal": {
                  "Value": "'Center'"
                }
              }
            },
            "styleHeader": {
              "expr": {
                "Literal": {
                  "Value": "true"
                }
              }
            },
            "styleValues": {
              "expr": {
                "Literal": {
                  "Value": "false"
                }
              }
            },
            "styleSubtotals": {
              "expr": {
                "Literal": {
                  "Value": "false"
                }
              }
            },
            "styleTotal": {
              "expr": {
                "Literal": {
                  "Value": "false"
                }
              }
            }
          },
          "selector": {
            "metadata": "1 - Revenue.Volume Variance"
          }
        },
        {
          "properties": {
            "alignment": {
              "expr": {
                "Literal": {
                  "Value": "'Center'"
                }
              }
            },
            "styleHeader": {
              "expr": {
                "Literal": {
                  "Value": "true"
                }
              }
            },
            "styleValues": {
              "expr": {
                "Literal": {
                  "Value": "false"
                }
              }
            },
            "styleSubtotals": {
              "expr": {
                "Literal": {
                  "Value": "false"
                }
              }
            },
            "styleTotal": {
              "expr": {
                "Literal": {
                  "Value": "false"
                }
              }
            }
          },
          "selector": {
            "metadata": "1 - Revenue.Total Variance"
          }
        },
        {
          "properties": {
            "alignment": {
              "expr": {
                "Literal": {
                  "Value": "'Center'"
                }
              }
            },
            "styleHeader": {
              "expr": {
                "Literal": {
                  "Value": "true"
                }
              }
            },
            "styleValues": {
              "expr": {
                "Literal": {
                  "Value": "false"
                }
              }
            },
            "styleSubtotals": {
              "expr": {
                "Literal": {
                  "Value": "false"
                }
              }
            }
          },
          "selector": {
            "metadata": "1 - Revenue.∆ Price"
          }
        },
        {
          "properties": {
            "alignment": {
              "expr": {
                "Literal": {
                  "Value": "'Center'"
                }
              }
            },
            "styleHeader": {
              "expr": {
                "Literal": {
                  "Value": "true"
                }
              }
            },
            "styleValues": {
              "expr": {
                "Literal": {
                  "Value": "false"
                }
              }
            },
            "styleSubtotals": {
              "expr": {
                "Literal": {
                  "Value": "false"
                }
              }
            }
          },
          "selector": {
            "metadata": "1 - Revenue.∆ Vol."
          }
        }
      ],
      "rowTotal": [
        {
          "properties": {
            "fontSize": {
              "expr": {
                "Literal": {
                  "Value": "9D"
                }
              }
            }
          }
        }
      ]
    },
    "visualContainerObjects": {
      "dropShadow": [
        {
          "properties": {
            "show": {
              "expr": {
                "Literal": {
                  "Value": "false"
                }
              }
            },
            "preset": {
              "expr": {
                "Literal": {
                  "Value": "'Custom'"
                }
              }
            },
            "position": {
              "expr": {
                "Literal": {
                  "Value": "'Outer'"
                }
              }
            },
            "color": {
              "solid": {
                "color": {
                  "expr": {
                    "Literal": {
                      "Value": "'#001A29'"
                    }
                  }
                }
              }
            },
            "transparency": {
              "expr": {
                "Literal": {
                  "Value": "75D"
                }
              }
            },
            "shadowSpread": {
              "expr": {
                "Literal": {
                  "Value": "0D"
                }
              }
            },
            "shadowBlur": {
              "expr": {
                "Literal": {
                  "Value": "10D"
                }
              }
            },
            "angle": {
              "expr": {
                "Literal": {
                  "Value": "45D"
                }
              }
            },
            "shadowDistance": {
              "expr": {
                "Literal": {
                  "Value": "10D"
                }
              }
            }
          }
        }
      ],
      "border": [
        {
          "properties": {
            "show": {
              "expr": {
                "Literal": {
                  "Value": "true"
                }
              }
            },
            "color": {
              "solid": {
                "color": {
                  "expr": {
                    "ThemeDataColor": {
                      "ColorId": 0,
                      "Percent": -0.3
                    }
                  }
                }
              }
            },
            "radius": {
              "expr": {
                "Literal": {
                  "Value": "0D"
                }
              }
            },
            "width": {
              "expr": {
                "Literal": {
                  "Value": "1D"
                }
              }
            }
          }
        }
      ],
      "title": [
        {
          "properties": {
            "text": {
              "expr": {
                "Literal": {
                  "Value": "'PRICE - VOL CALCULATION'"
                }
              }
            },
            "show": {
              "expr": {
                "Literal": {
                  "Value": "true"
                }
              }
            },
            "titleWrap": {
              "expr": {
                "Literal": {
                  "Value": "true"
                }
              }
            }
          }
        }
      ],
      "subTitle": [
        {
          "properties": {
            "text": {
              "expr": {
                "Literal": {
                  "Value": "'  '"
                }
              }
            },
            "show": {
              "expr": {
                "Literal": {
                  "Value": "true"
                }
              }
            },
            "fontSize": {
              "expr": {
                "Literal": {
                  "Value": "8D"
                }
              }
            }
          }
        }
      ],
      "spacing": [
        {
          "properties": {
            "verticalSpacing": {
              "expr": {
                "Literal": {
                  "Value": "0D"
                }
              }
            }
          }
        }
      ],
      "background": [
        {
          "properties": {
            "show": {
              "expr": {
                "Literal": {
                  "Value": "true"
                }
              }
            },
            "color": {
              "solid": {
                "color": {
                  "expr": {
                    "Literal": {
                      "Value": "'#FFFFFF'"
                    }
                  }
                }
              }
            },
            "transparency": {
              "expr": {
                "Literal": {
                  "Value": "0D"
                }
              }
            }
          }
        }
      ],
      "padding": [
        {
          "properties": {
            "top": {
              "expr": {
                "Literal": {
                  "Value": "0D"
                }
              }
            },
            "bottom": {
              "expr": {
                "Literal": {
                  "Value": "5D"
                }
              }
            },
            "left": {
              "expr": {
                "Literal": {
                  "Value": "5D"
                }
              }
            },
            "right": {
              "expr": {
                "Literal": {
                  "Value": "5D"
                }
              }
            }
          }
        }
      ],
      "visualHeader": [
        {
          "properties": {
            "show": {
              "expr": {
                "Literal": {
                  "Value": "false"
                }
              }
            }
          }
        }
      ]
    },
    "drillFilterOtherVisuals": true
  },
  "parentGroupName": "fb32a4a1871273ec9a78"
}