{
  "$schema": "https://developer.microsoft.com/json-schemas/fabric/item/report/definition/visualContainer/2.1.0/schema.json",
  "name": "89bc92b8b01e00c39803",
  "position": {
    "x": 36.200145032632342,
    "y": 83.538796229151558,
    "z": 1000,
    "height": 974.61928934010143,
    "width": 636.28716461203771,
    "tabOrder": 2000
  },
  "visual": {
    "visualType": "pivotTable",
    "query": {
      "queryState": {
        "Columns": {
          "projections": [
            {
              "field": {
                "Column": {
                  "Expression": {
                    "SourceRef": {
                      "Entity": "MBR_Columns"
                    }
                  },
                  "Property": "Time Intelligence"
                }
              },
              "queryRef": "MBR_Columns.Time Intelligence",
              "nativeQueryRef": "Time Intelligence",
              "active": true
            }
          ],
          "showAll": true
        },
        "Rows": {
          "projections": [
            {
              "field": {
                "Column": {
                  "Expression": {
                    "SourceRef": {
                      "Entity": "Product"
                    }
                  },
                  "Property": "Product"
                }
              },
              "queryRef": "Product.Product",
              "nativeQueryRef": "Product",
              "active": true
            }
          ],
          "showAll": true
        },
        "Values": {
          "projections": [
            {
              "field": {
                "Measure": {
                  "Expression": {
                    "SourceRef": {
                      "Entity": "BPC Profit"
                    }
                  },
                  "Property": "Net Revenue Actual"
                }
              },
              "queryRef": "Profit.Income Actual",
              "nativeQueryRef": "Income Actual"
            },
            {
              "field": {
                "Measure": {
                  "Expression": {
                    "SourceRef": {
                      "Entity": "BPC Profit"
                    }
                  },
                  "Property": "Operating Income or Loss Actual"
                }
              },
              "queryRef": "Profit.Product Margin Actual",
              "nativeQueryRef": "Product Margin Actual"
            },
            {
              "field": {
                "Measure": {
                  "Expression": {
                    "SourceRef": {
                      "Entity": "BPC Profit"
                    }
                  },
                  "Property": "EBIT Actual"
                }
              },
              "queryRef": "Profit.Gross Margin Actual",
              "nativeQueryRef": "Gross Margin Actual"
            },
            {
              "field": {
                "Measure": {
                  "Expression": {
                    "SourceRef": {
                      "Entity": "BPC Profit"
                    }
                  },
                  "Property": "EBITDA Actual"
                }
              },
              "queryRef": "Profit.EBITDA Actual",
              "nativeQueryRef": "EBITDA Actual"
            }
          ]
        }
      }
    },
    "objects": {
      "general": [
        {
          "properties": {}
        }
      ],
      "values": [
        {
          "properties": {
            "valuesOnRow": {
              "expr": {
                "Literal": {
                  "Value": "true"
                }
              }
            }
          }
        }
      ]
    },
    "visualContainerObjects": {
      "title": [
        {
          "properties": {
            "text": {
              "expr": {
                "Literal": {
                  "Value": "'Product Performance - Current vs Previous Quarter'"
                }
              }
            },
            "fontSize": {
              "expr": {
                "Literal": {
                  "Value": "12D"
                }
              }
            }
          }
        }
      ],
      "dropShadow": [
        {
          "properties": {
            "show": {
              "expr": {
                "Literal": {
                  "Value": "false"
                }
              }
            }
          }
        }
      ],
      "visualHeader": [
        {
          "properties": {
            "show": {
              "expr": {
                "Literal": {
                  "Value": "true"
                }
              }
            }
          }
        }
      ],
      "padding": [
        {
          "properties": {
            "top": {
              "expr": {
                "Literal": {
                  "Value": "0D"
                }
              }
            },
            "left": {
              "expr": {
                "Literal": {
                  "Value": "5D"
                }
              }
            },
            "bottom": {
              "expr": {
                "Literal": {
                  "Value": "0D"
                }
              }
            },
            "right": {
              "expr": {
                "Literal": {
                  "Value": "0D"
                }
              }
            }
          }
        }
      ],
      "border": [
        {
          "properties": {
            "color": {
              "solid": {
                "color": {
                  "expr": {
                    "ThemeDataColor": {
                      "ColorId": 0,
                      "Percent": -0.3
                    }
                  }
                }
              }
            },
            "radius": {
              "expr": {
                "Literal": {
                  "Value": "10D"
                }
              }
            }
          }
        }
      ],
      "subTitle": [
        {
          "properties": {
            "show": {
              "expr": {
                "Literal": {
                  "Value": "false"
                }
              }
            },
            "fontSize": {
              "expr": {
                "Literal": {
                  "Value": "8D"
                }
              }
            },
            "text": {
              "expr": {
                "Literal": {
                  "Value": "'🔵Actual  🔲 Forecast'"
                }
              }
            }
          }
        }
      ]
    },
    "drillFilterOtherVisuals": true
  },
  "filterConfig": {
    "filters": [
      {
        "name": "fe1c7226ed2814335425",
        "field": {
          "Column": {
            "Expression": {
              "SourceRef": {
                "Entity": "Date Table"
              }
            },
            "Property": "Quarter Offset"
          }
        },
        "type": "Advanced",
        "filter": {
          "Version": 2,
          "From": [
            {
              "Name": "d",
              "Entity": "Date Table",
              "Type": 0
            }
          ],
          "Where": [
            {
              "Condition": {
                "Comparison": {
                  "ComparisonKind": 2,
                  "Left": {
                    "Column": {
                      "Expression": {
                        "SourceRef": {
                          "Source": "d"
                        }
                      },
                      "Property": "Quarter Offset"
                    }
                  },
                  "Right": {
                    "Literal": {
                      "Value": "-1L"
                    }
                  }
                }
              }
            }
          ]
        },
        "howCreated": "User"
      },
      {
        "name": "424d92e6e5e4c3200380",
        "field": {
          "Column": {
            "Expression": {
              "SourceRef": {
                "Entity": "MBR_Columns"
              }
            },
            "Property": "Time Intelligence"
          }
        },
        "type": "Categorical",
        "filter": {
          "Version": 2,
          "From": [
            {
              "Name": "m",
              "Entity": "MBR_Columns",
              "Type": 0
            }
          ],
          "Where": [
            {
              "Condition": {
                "In": {
                  "Expressions": [
                    {
                      "Column": {
                        "Expression": {
                          "SourceRef": {
                            "Source": "m"
                          }
                        },
                        "Property": "Time Intelligence"
                      }
                    }
                  ],
                  "Values": [
                    [
                      {
                        "Literal": {
                          "Value": "'Current Quarter'"
                        }
                      }
                    ],
                    [
                      {
                        "Literal": {
                          "Value": "'Q-1'"
                        }
                      }
                    ],
                    [
                      {
                        "Literal": {
                          "Value": "'Var Q vs Q-1'"
                        }
                      }
                    ]
                  ]
                }
              }
            }
          ]
        }
      }
    ]
  },
  "isHidden": true
}